baccarat/__init__.py
baccarat/py.typed
baccarat/simulator.py
baccarat/params/__init__.py
baccarat/params/base.py
baccarat/params/gaussian.py
baccarat/params/static.py
baccarat/params/uniform.py
baccarat_sim-0.1.0.dist-info/METADATA
baccarat_sim-0.1.0.dist-info/WHEEL
baccarat_sim-0.1.0.dist-info/licenses/LICENSE
baccarat_sim-0.1.0.dist-info/RECORD
