Metadata-Version: 2.4
Name: baccarat_sim
Version: 0.1.0
Summary: Monte Carlo simulation framework in Python
Author-email: Mathias Alexander <mathias@mathias-alexander.com>
License-File: LICENSE
Requires-Python: >=3.13
Requires-Dist: numpy>=2.2.3
